agenthink/__init__.py
agenthink/connection.py
agenthink/data_source.py
agenthink/models.py
agenthink/utils.py
agenthink-0.1.27.dist-info/METADATA
agenthink-0.1.27.dist-info/WHEEL
agenthink-0.1.27.dist-info/top_level.txt
agenthink-0.1.27.dist-info/RECORD
