Metadata-Version: 2.4
Name: agenthink
Version: 0.1.27
Summary: A unified agent framework for connecting workflows, databases, and agents
Author: Ritobroto
Requires-Python: >=3.10
Requires-Dist: fastapi
Requires-Dist: mysql-connector-python
Requires-Dist: azure-identity
Requires-Dist: azure-keyvault-secrets
Requires-Dist: azure-storage-blob
Requires-Dist: pyodbc
Requires-Dist: python-dotenv
